cosched/__init__.py
cosched-0.0.0.dist-info/LICENSE
cosched-0.0.0.dist-info/METADATA
cosched-0.0.0.dist-info/WHEEL
cosched-0.0.0.dist-info/top_level.txt
cosched-0.0.0.dist-info/RECORD
